{
  "phase": 112,
  "title": "Dirac Equation from Coordination",
  "breakthrough_number": 53,
  "question_answered": "Q475",
  "answer": "YES - Dirac equation emerges uniquely from coordination + relativity",
  "key_results": [
    "SWAP symmetry -> spin-1/2 (from Phase 110)",
    "Relativity requires linearization of E^2 = p^2 + m^2",
    "Clifford algebra Cl(3,1) gives unique 4x4 gamma matrices",
    "Tensor product structure: spin x particle/antiparticle",
    "Dirac equation is UNIQUE first-order relativistic wave equation"
  ],
  "derived_results": [
    "Antimatter existence (from tensor structure)",
    "CPT symmetry (from Lorentz + tensor structure)",
    "g = 2 exactly (from spin-orbit coupling)",
    "Spinor transformation properties"
  ],
  "new_questions": [
    "Q489: Full QED Lagrangian from coordination",
    "Q490: Neutrino masses",
    "Q491: Weak SU(2) from SWAP extension",
    "Q492: Chirality interpretation",
    "Q493: Three fermion generations",
    "Q494: Dirac sea interpretation",
    "Q495: Pauli exclusion from SWAP"
  ],
  "master_equation_validations": 11,
  "phases_completed": 112,
  "total_questions": 495,
  "questions_answered": 113,
  "confidence": "VERY HIGH"
}